odoo8_addon_partner_noncommercial-8.0.1.0.0-py2.7-nspkg.pth
odoo8_addon_partner_noncommercial-8.0.1.0.0.dist-info/DESCRIPTION.rst
odoo8_addon_partner_noncommercial-8.0.1.0.0.dist-info/METADATA
odoo8_addon_partner_noncommercial-8.0.1.0.0.dist-info/RECORD
odoo8_addon_partner_noncommercial-8.0.1.0.0.dist-info/WHEEL
odoo8_addon_partner_noncommercial-8.0.1.0.0.dist-info/metadata.json
odoo8_addon_partner_noncommercial-8.0.1.0.0.dist-info/namespace_packages.txt
odoo8_addon_partner_noncommercial-8.0.1.0.0.dist-info/top_level.txt
odoo_addons/partner_noncommercial/README.rst
odoo_addons/partner_noncommercial/__init__.py
odoo_addons/partner_noncommercial/__openerp__.py
odoo_addons/partner_noncommercial/data/ir_translation.xml
odoo_addons/partner_noncommercial/i18n/nl.po
odoo_addons/partner_noncommercial/i18n/partner_noncommercial.pot
odoo_addons/partner_noncommercial/i18n_extra/en.po
odoo_addons/partner_noncommercial/i18n_extra/nl.po
odoo_addons/partner_noncommercial/views/menu.xml
odoo_addons/partner_noncommercial/views/res_partner.xml
